deepfmkit/__init__.py
deepfmkit/core.py
deepfmkit/data.py
deepfmkit/dsp.py
deepfmkit/experiments.py
deepfmkit/factories.py
deepfmkit/fit.py
deepfmkit/fitters.py
deepfmkit/helpers.py
deepfmkit/noise.py
deepfmkit/physics.py
deepfmkit/plotting.py
deepfmkit/waveforms.py
deepfmkit-1.0.4.dist-info/licenses/AUTHORS
deepfmkit-1.0.4.dist-info/licenses/LICENSE
deepfmkit-1.0.4.dist-info/METADATA
deepfmkit-1.0.4.dist-info/WHEEL
deepfmkit-1.0.4.dist-info/top_level.txt
deepfmkit-1.0.4.dist-info/RECORD
