Metadata-Version: 2.4
Name: deepfmkit
Version: 1.0.4
Summary: A Python toolkit for Deep Frequency Modulation Interferometry.
Author-email: Miguel Dovale <spectools@pm.me>
License: BSD 3-Clause License
Project-URL: Homepage, https://github.com/mdovale/DeepFMKit
Project-URL: Repository, https://github.com/mdovale/DeepFMKit
Project-URL: Issues, https://github.com/mdovale/DeepFMKit/issues
Classifier: Programming Language :: Python :: 3
Classifier: License :: OSI Approved :: BSD License
Classifier: Operating System :: OS Independent
Classifier: Intended Audience :: Science/Research
Classifier: Topic :: Scientific/Engineering :: Physics
Requires-Python: >=3.9
License-File: LICENSE
License-File: AUTHORS
Requires-Dist: numpy
Requires-Dist: scipy
Requires-Dist: pandas
Requires-Dist: matplotlib
Requires-Dist: numba
Requires-Dist: tqdm
Provides-Extra: dev
Requires-Dist: pytest; extra == "dev"
Requires-Dist: build; extra == "dev"
Requires-Dist: twine; extra == "dev"
Requires-Dist: ruff; extra == "dev"
Dynamic: license-file
